{
  "metadata": {
    "generado": "2026-07-19T01:43:57Z",
    "fuente": "https://earthquake.usgs.gov/fdsnws/event/1/query",
    "rango_fechas": {
      "desde": "2016-07-21",
      "hasta": "2026-07-19"
    },
    "clustering": {
      "algoritmo": "HDBSCAN",
      "min_cluster_size": 20,
      "min_samples": 8
    },
    "criterio_posible_replica": "cluster != -1 y menos de 1 hora(s) desde el evento anterior del mismo cluster",
    "total_eventos": 8523,
    "total_clusters": 58
  },
  "clusters": [
    {
      "id": 47,
      "region": "continental",
      "lat": -24.1469,
      "lon": -67.0554,
      "n": 1042,
      "mag_media": 4.36,
      "mag_max": 6.4,
      "fecha_ultimo_evento": "2026-07-17T22:35:28Z"
    },
    {
      "id": 56,
      "region": "continental",
      "lat": -21.903,
      "lon": -68.597,
      "n": 403,
      "mag_media": 4.37,
      "mag_max": 6.2,
      "fecha_ultimo_evento": "2026-06-28T21:53:27Z"
    },
    {
      "id": 57,
      "region": "continental",
      "lat": -21.1783,
      "lon": -68.7558,
      "n": 286,
      "mag_media": 4.3,
      "mag_max": 5.4,
      "fecha_ultimo_evento": "2026-07-12T22:15:43Z"
    },
    {
      "id": 4,
      "region": "continental",
      "lat": -36.8335,
      "lon": -73.7534,
      "n": 256,
      "mag_media": 4.47,
      "mag_max": 6.7,
      "fecha_ultimo_evento": "2026-05-19T07:31:32Z"
    },
    {
      "id": 44,
      "region": "continental",
      "lat": -21.7327,
      "lon": -67.4734,
      "n": 241,
      "mag_media": 4.34,
      "mag_max": 5.8,
      "fecha_ultimo_evento": "2026-07-17T22:59:11Z"
    },
    {
      "id": 16,
      "region": "continental",
      "lat": -31.5581,
      "lon": -69.0275,
      "n": 231,
      "mag_media": 4.46,
      "mag_max": 6.4,
      "fecha_ultimo_evento": "2026-07-06T08:56:01Z"
    },
    {
      "id": 46,
      "region": "continental",
      "lat": -22.7944,
      "lon": -66.3317,
      "n": 149,
      "mag_media": 4.4,
      "mag_max": 6.0,
      "fecha_ultimo_evento": "2026-06-20T01:22:21Z"
    },
    {
      "id": 49,
      "region": "continental",
      "lat": -17.7555,
      "lon": -69.7068,
      "n": 144,
      "mag_media": 4.38,
      "mag_max": 6.3,
      "fecha_ultimo_evento": "2026-04-19T18:20:00Z"
    },
    {
      "id": 39,
      "region": "continental",
      "lat": -30.7492,
      "lon": -71.4554,
      "n": 111,
      "mag_media": 4.46,
      "mag_max": 6.2,
      "fecha_ultimo_evento": "2026-07-04T03:09:33Z"
    },
    {
      "id": 53,
      "region": "continental",
      "lat": -20.18,
      "lon": -69.1383,
      "n": 108,
      "mag_media": 4.38,
      "mag_max": 6.1,
      "fecha_ultimo_evento": "2026-05-26T16:42:41Z"
    },
    {
      "id": 36,
      "region": "continental",
      "lat": -33.1098,
      "lon": -72.0762,
      "n": 106,
      "mag_media": 4.5,
      "mag_max": 6.9,
      "fecha_ultimo_evento": "2024-12-25T23:14:32Z"
    },
    {
      "id": 29,
      "region": "continental",
      "lat": -27.9118,
      "lon": -71.4097,
      "n": 103,
      "mag_media": 4.52,
      "mag_max": 6.8,
      "fecha_ultimo_evento": "2026-06-12T04:23:27Z"
    },
    {
      "id": 31,
      "region": "continental",
      "lat": -21.4356,
      "lon": -66.7659,
      "n": 100,
      "mag_media": 4.38,
      "mag_max": 5.4,
      "fecha_ultimo_evento": "2026-05-31T12:37:12Z"
    },
    {
      "id": 48,
      "region": "continental",
      "lat": -23.3441,
      "lon": -66.8142,
      "n": 100,
      "mag_media": 4.34,
      "mag_max": 5.2,
      "fecha_ultimo_evento": "2026-06-12T17:54:29Z"
    },
    {
      "id": 28,
      "region": "continental",
      "lat": -30.0946,
      "lon": -72.0961,
      "n": 98,
      "mag_media": 4.48,
      "mag_max": 6.4,
      "fecha_ultimo_evento": "2026-05-06T11:31:44Z"
    },
    {
      "id": 43,
      "region": "continental",
      "lat": -30.4872,
      "lon": -71.6716,
      "n": 90,
      "mag_media": 4.44,
      "mag_max": 6.3,
      "fecha_ultimo_evento": "2026-05-27T04:17:23Z"
    },
    {
      "id": 23,
      "region": "continental",
      "lat": -20.0117,
      "lon": -70.9465,
      "n": 84,
      "mag_media": 4.47,
      "mag_max": 5.5,
      "fecha_ultimo_evento": "2026-05-14T22:06:27Z"
    },
    {
      "id": 27,
      "region": "continental",
      "lat": -33.9212,
      "lon": -72.3665,
      "n": 83,
      "mag_media": 4.52,
      "mag_max": 6.0,
      "fecha_ultimo_evento": "2026-06-03T22:36:06Z"
    },
    {
      "id": 15,
      "region": "continental",
      "lat": -33.3505,
      "lon": -70.2753,
      "n": 81,
      "mag_media": 4.4,
      "mag_max": 5.7,
      "fecha_ultimo_evento": "2026-04-19T02:09:08Z"
    },
    {
      "id": 7,
      "region": "continental",
      "lat": -27.9205,
      "lon": -66.7172,
      "n": 80,
      "mag_media": 4.47,
      "mag_max": 5.3,
      "fecha_ultimo_evento": "2026-04-25T02:56:29Z"
    },
    {
      "id": 6,
      "region": "continental",
      "lat": -28.3651,
      "lon": -67.444,
      "n": 75,
      "mag_media": 4.49,
      "mag_max": 5.9,
      "fecha_ultimo_evento": "2026-03-13T14:58:59Z"
    },
    {
      "id": 30,
      "region": "continental",
      "lat": -28.7252,
      "lon": -71.5043,
      "n": 70,
      "mag_media": 4.56,
      "mag_max": 6.6,
      "fecha_ultimo_evento": "2026-04-26T20:08:06Z"
    },
    {
      "id": 1,
      "region": "continental",
      "lat": -42.8053,
      "lon": -74.2743,
      "n": 66,
      "mag_media": 4.43,
      "mag_max": 7.6,
      "fecha_ultimo_evento": "2026-07-02T16:35:09Z"
    },
    {
      "id": 10,
      "region": "continental",
      "lat": -27.9276,
      "lon": -69.1979,
      "n": 64,
      "mag_media": 4.44,
      "mag_max": 5.6,
      "fecha_ultimo_evento": "2026-07-03T16:03:52Z"
    },
    {
      "id": 3,
      "region": "continental",
      "lat": -38.9807,
      "lon": -75.1178,
      "n": 60,
      "mag_media": 4.45,
      "mag_max": 6.7,
      "fecha_ultimo_evento": "2026-07-02T00:25:19Z"
    },
    {
      "id": 24,
      "region": "continental",
      "lat": -21.1806,
      "lon": -69.9537,
      "n": 59,
      "mag_media": 4.31,
      "mag_max": 6.2,
      "fecha_ultimo_evento": "2026-05-25T07:12:40Z"
    },
    {
      "id": 55,
      "region": "continental",
      "lat": -20.7608,
      "lon": -69.1073,
      "n": 53,
      "mag_media": 4.3,
      "mag_max": 4.9,
      "fecha_ultimo_evento": "2026-05-25T11:15:56Z"
    },
    {
      "id": 8,
      "region": "continental",
      "lat": -31.655,
      "lon": -67.2076,
      "n": 50,
      "mag_media": 4.46,
      "mag_max": 6.0,
      "fecha_ultimo_evento": "2026-06-05T06:54:48Z"
    },
    {
      "id": 21,
      "region": "continental",
      "lat": -22.4837,
      "lon": -70.3735,
      "n": 50,
      "mag_media": 4.33,
      "mag_max": 6.1,
      "fecha_ultimo_evento": "2026-06-22T13:18:42Z"
    },
    {
      "id": 33,
      "region": "continental",
      "lat": -31.7371,
      "lon": -72.1153,
      "n": 50,
      "mag_media": 4.32,
      "mag_max": 5.9,
      "fecha_ultimo_evento": "2026-06-02T09:53:45Z"
    },
    {
      "id": 11,
      "region": "continental",
      "lat": -35.3383,
      "lon": -71.2283,
      "n": 49,
      "mag_media": 4.41,
      "mag_max": 6.3,
      "fecha_ultimo_evento": "2026-06-20T19:45:25Z"
    },
    {
      "id": 18,
      "region": "continental",
      "lat": -18.482,
      "lon": -71.2449,
      "n": 49,
      "mag_media": 4.37,
      "mag_max": 5.6,
      "fecha_ultimo_evento": "2026-05-29T05:32:39Z"
    },
    {
      "id": 20,
      "region": "continental",
      "lat": -25.7418,
      "lon": -70.977,
      "n": 46,
      "mag_media": 4.45,
      "mag_max": 5.7,
      "fecha_ultimo_evento": "2026-06-07T19:40:58Z"
    },
    {
      "id": 14,
      "region": "continental",
      "lat": -19.13,
      "lon": -67.0802,
      "n": 45,
      "mag_media": 4.39,
      "mag_max": 5.7,
      "fecha_ultimo_evento": "2026-03-24T02:03:10Z"
    },
    {
      "id": 26,
      "region": "continental",
      "lat": -19.5107,
      "lon": -70.1332,
      "n": 45,
      "mag_media": 4.42,
      "mag_max": 5.9,
      "fecha_ultimo_evento": "2026-06-19T06:13:07Z"
    },
    {
      "id": 37,
      "region": "continental",
      "lat": -32.1399,
      "lon": -71.8639,
      "n": 45,
      "mag_media": 4.3,
      "mag_max": 5.2,
      "fecha_ultimo_evento": "2026-06-08T06:13:52Z"
    },
    {
      "id": 34,
      "region": "continental",
      "lat": -29.5166,
      "lon": -71.3272,
      "n": 42,
      "mag_media": 4.46,
      "mag_max": 5.8,
      "fecha_ultimo_evento": "2026-03-04T11:48:34Z"
    },
    {
      "id": 35,
      "region": "continental",
      "lat": -31.835,
      "lon": -71.4957,
      "n": 42,
      "mag_media": 4.42,
      "mag_max": 6.1,
      "fecha_ultimo_evento": "2026-05-17T02:41:41Z"
    },
    {
      "id": 38,
      "region": "continental",
      "lat": -32.6061,
      "lon": -71.8167,
      "n": 41,
      "mag_media": 4.36,
      "mag_max": 5.1,
      "fecha_ultimo_evento": "2026-07-15T01:09:20Z"
    },
    {
      "id": 17,
      "region": "continental",
      "lat": -34.7891,
      "lon": -71.8092,
      "n": 37,
      "mag_media": 4.38,
      "mag_max": 5.5,
      "fecha_ultimo_evento": "2026-06-13T22:29:11Z"
    },
    {
      "id": 51,
      "region": "continental",
      "lat": -19.2268,
      "lon": -69.394,
      "n": 33,
      "mag_media": 4.42,
      "mag_max": 5.5,
      "fecha_ultimo_evento": "2026-05-06T11:25:51Z"
    },
    {
      "id": 54,
      "region": "continental",
      "lat": -20.515,
      "lon": -68.8754,
      "n": 33,
      "mag_media": 4.26,
      "mag_max": 4.7,
      "fecha_ultimo_evento": "2026-06-04T21:59:25Z"
    },
    {
      "id": 19,
      "region": "continental",
      "lat": -17.5061,
      "lon": -70.6411,
      "n": 31,
      "mag_media": 4.45,
      "mag_max": 5.2,
      "fecha_ultimo_evento": "2026-04-13T20:42:49Z"
    },
    {
      "id": 9,
      "region": "continental",
      "lat": -29.3131,
      "lon": -69.5467,
      "n": 30,
      "mag_media": 4.51,
      "mag_max": 5.8,
      "fecha_ultimo_evento": "2026-05-13T10:18:42Z"
    },
    {
      "id": 32,
      "region": "continental",
      "lat": -23.2624,
      "lon": -67.8308,
      "n": 28,
      "mag_media": 4.59,
      "mag_max": 7.4,
      "fecha_ultimo_evento": "2026-02-18T19:32:14Z"
    },
    {
      "id": 42,
      "region": "continental",
      "lat": -30.0888,
      "lon": -71.3644,
      "n": 28,
      "mag_media": 4.44,
      "mag_max": 6.7,
      "fecha_ultimo_evento": "2026-07-16T10:38:08Z"
    },
    {
      "id": 5,
      "region": "continental",
      "lat": -34.8577,
      "lon": -73.8952,
      "n": 27,
      "mag_media": 4.45,
      "mag_max": 5.4,
      "fecha_ultimo_evento": "2025-12-07T09:35:45Z"
    },
    {
      "id": 52,
      "region": "continental",
      "lat": -19.6512,
      "lon": -69.2636,
      "n": 27,
      "mag_media": 4.39,
      "mag_max": 6.2,
      "fecha_ultimo_evento": "2026-01-02T18:49:36Z"
    },
    {
      "id": 25,
      "region": "continental",
      "lat": -27.1106,
      "lon": -71.1947,
      "n": 26,
      "mag_media": 4.46,
      "mag_max": 5.5,
      "fecha_ultimo_evento": "2026-05-04T08:22:01Z"
    },
    {
      "id": 0,
      "region": "continental",
      "lat": -51.6049,
      "lon": -72.7447,
      "n": 25,
      "mag_media": 4.45,
      "mag_max": 5.4,
      "fecha_ultimo_evento": "2026-04-15T02:38:27Z"
    },
    {
      "id": 41,
      "region": "continental",
      "lat": -29.915,
      "lon": -71.6712,
      "n": 24,
      "mag_media": 4.31,
      "mag_max": 5.0,
      "fecha_ultimo_evento": "2025-10-24T19:56:14Z"
    },
    {
      "id": 13,
      "region": "continental",
      "lat": -25.7025,
      "lon": -69.3383,
      "n": 23,
      "mag_media": 4.36,
      "mag_max": 5.1,
      "fecha_ultimo_evento": "2025-08-15T23:39:32Z"
    },
    {
      "id": 22,
      "region": "continental",
      "lat": -20.8482,
      "lon": -70.6205,
      "n": 23,
      "mag_media": 4.45,
      "mag_max": 5.5,
      "fecha_ultimo_evento": "2025-07-27T04:28:59Z"
    },
    {
      "id": 2,
      "region": "continental",
      "lat": -17.6449,
      "lon": -72.7412,
      "n": 22,
      "mag_media": 4.52,
      "mag_max": 5.5,
      "fecha_ultimo_evento": "2025-08-25T09:40:28Z"
    },
    {
      "id": 40,
      "region": "continental",
      "lat": -23.6722,
      "lon": -68.0879,
      "n": 22,
      "mag_media": 4.3,
      "mag_max": 5.0,
      "fecha_ultimo_evento": "2025-11-26T10:53:45Z"
    },
    {
      "id": 12,
      "region": "continental",
      "lat": -24.477,
      "lon": -70.1493,
      "n": 20,
      "mag_media": 4.58,
      "mag_max": 5.4,
      "fecha_ultimo_evento": "2026-01-12T07:57:32Z"
    },
    {
      "id": 45,
      "region": "continental",
      "lat": -22.8607,
      "lon": -68.1189,
      "n": 20,
      "mag_media": 4.62,
      "mag_max": 5.7,
      "fecha_ultimo_evento": "2025-09-29T01:58:42Z"
    },
    {
      "id": 50,
      "region": "continental",
      "lat": -22.9546,
      "lon": -68.8899,
      "n": 20,
      "mag_media": 4.4,
      "mag_max": 5.1,
      "fecha_ultimo_evento": "2025-12-02T02:36:29Z"
    }
  ]
}